[
  {
    "id": "1759583809482",
    "title": "KIT CREATINA",
    "price": "129",
    "description": "A creatina em c脙聝脗聝脙聜脗聝脙聝脗聜脙聜脗聝脙聝脗聝脙聜脗聜脙聝脗聜脙聜脗聝脙聝脗聝脙聜脗聝脙聝脗聜脙聜脗聜脙聝脗聝脙聜脗聜脙聝脗聜脙聜脗隆psula 脙聝脗聝脙聜脗聝脙聝脗聜脙聜脗聝脙聝脗聝脙聜脗聜脙聝脗聜脙聜脗聝脙聝脗聝脙聜脗聝脙聝脗聜脙聜脗聜脙聝脗聝脙聜脗聜脙聝脗聜脙聜脗漏 uma forma pr脙聝脗聝脙聜脗聝脙聝脗聜脙聜脗聝脙聝脗聝脙聜脗聜脙聝脗聜脙聜脗聝脙聝脗聝脙聜脗聝脙聝脗聜脙聜脗聜脙聝脗聝脙聜脗聜脙聝脗聜脙聜脗隆tica e conveniente de suplementa脙聝脗聝脙聜脗聝脙聝脗聜脙聜脗聝脙聝脗聝脙聜脗聜脙聝脗聜脙聜脗聝脙聝脗聝脙聜脗聝脙聝脗聜脙聜脗聜脙聝脗聝脙聜脗聜脙聝脗聜脙聜脗搂脙聝脗聝脙聜脗聝脙聝脗聜脙聜脗聝脙聝脗聝脙聜脗聜脙聝脗聜脙聜脗聝脙聝脗聝脙聜脗聝脙聝脗聜脙聜脗聜脙聝脗聝脙聜脗聜脙聝脗聜脙聜脗拢o que oferece os mesmos benef脙聝脗聝脙聜脗聝脙聝脗聜脙聜脗聝脙聝脗聝脙聜脗聜脙聝脗聜脙聜脗聝脙聝脗聝脙聜脗聝脙聝脗聜脙聜脗聜脙聝脗聝脙聜脗聜脙聝脗聜脙聜脗颅cios da creatina em p脙聝脗聝脙聜脗聝脙聝脗聜脙聜脗聝脙聝脗聝脙聜脗聜脙聝脗聜脙聜脗聝脙聝脗聝脙聜脗聝脙聝脗聜脙聜脗聜脙聝脗聝脙聜脗聜脙聝脗聜脙聜脗鲁, principalmente para aumento da for脙聝脗聝脙聜脗聝脙聝脗聜脙聜脗聝脙聝脗聝脙聜脗聜脙聝脗聜脙聜脗聝脙聝脗聝脙聜脗聝脙聝脗聜脙聜脗聜脙聝脗聝脙聜脗聜脙聝脗聜脙聜脗搂a, resist脙聝脗聝脙聜脗聝脙聝脗聜脙聜脗聝脙聝脗聝脙聜脗聜脙聝脗聜脙聜脗聝脙聝脗聝脙聜脗聝脙聝脗聜脙聜脗聜脙聝脗聝脙聜脗聜脙聝脗聜脙聜脗陋ncia e desempenho em exerc脙聝脗聝脙聜脗聝脙聝脗聜脙聜脗聝脙聝脗聝脙聜脗聜脙聝脗聜脙聜脗聝脙聝脗聝脙聜脗聝脙聝脗聜脙聜脗聜脙聝脗聝脙聜脗聜脙聝脗聜脙聜脗颅cios de alta intensidade e curta dura脙聝脗聝脙聜脗聝脙聝脗聜脙聜脗聝脙聝脗聝脙聜脗聜脙聝脗聜脙聜脗聝脙聝脗聝脙聜脗聝脙聝脗聜脙聜脗聜脙聝脗聝脙聜脗聜脙聝脗聜脙聜脗搂脙聝脗聝脙聜脗聝脙聝脗聜脙聜脗聝脙聝脗聝脙聜脗聜脙聝脗聜脙聜脗聝脙聝脗聝脙聜脗聝脙聝脗聜脙聜脗聜脙聝脗聝脙聜脗聜脙聝脗聜脙聜脗拢o",
    "category": "supplements",
    "stock": 70,
    "image": "https://raw.githubusercontent.com/STAVARENG0/hs/main/products/1759583809482/cratina em saco.png",
    "gallery": [
      "https://raw.githubusercontent.com/STAVARENG0/hs/main/products/1759583809482/cratina em saco.png",
      "https://raw.githubusercontent.com/STAVARENG0/hs/main/products/1759583809482/cratina grande.png",
      "https://raw.githubusercontent.com/STAVARENG0/hs/main/products/1759583809482/creatina em capisula.png",
      "https://raw.githubusercontent.com/STAVARENG0/hs/main/products/1759583809482/creatina.png"
    ],
    "createdAt": 1759583822106,
    "status": "publicado"
  },
  {
    "id": "1759593465773",
    "title": "CREATINA EM CAPISULA ",
    "price": "899",
    "description": "1000 脙聝脗聝脙聜脗聝脙聝脗聜脙聜脗聝脙聝脗聝脙聜脗聜脙聝脗聜脙聜脗聴 1000 px (quadrado)\n\nFormato: .JPG (qualidade alta, 80脙聝脗聝脙聜脗聝脙聝脗聜脙聜脗垄脙聝脗聝脙聜脗聜脙聝脗聜脙聜脗聙脙聝脗聝脙聜脗聜脙聝脗聜脙聜脗聯90% de compress脙聝脗聝脙聜脗聝脙聝脗聜脙聜脗聝脙聝脗聝脙聜脗聜脙聝脗聜脙聜脗拢o)\n\nFundo: branco, preto ou neutro (pra destacar o produto)\n\nPeso: at脙聝脗聝脙聜脗聝脙聝脗聜脙聜脗聝脙聝脗聝脙聜脗聜脙聝脗聜脙聜脗漏 250脙聝脗聝脙聜脗聝脙聝脗聜脙聜脗垄脙聝脗聝脙聜脗聜脙聝脗聜脙聜脗聙脙聝脗聝脙聜脗聜脙聝脗聜脙聜脗聯300 KB por imagem",
    "category": "supplements",
    "stock": 20,
    "image": "https://raw.githubusercontent.com/STAVARENG0/hs/main/products/1759593465773/Gemini_Generated_Image_u8drcvu8drcvu8dr.png",
    "gallery": [
      "https://raw.githubusercontent.com/STAVARENG0/hs/main/products/1759593465773/Gemini_Generated_Image_u8drcvu8drcvu8dr.png"
    ],
    "createdAt": 1759593469541,
    "status": "publicado"
  }
]