[
  {
    "id": "1777292949584",
    "title": "CORDA VERDE",
    "price": 1,
    "description": "CORDA DE PULA VERDE ",
    "department": "supplements",
    "category": "Vitamins & Minerals",
    "stock": 5,
    "image": "https://raw.githubusercontent.com/STAVARENG0/hs/main/products/1777292949584_1777292950015_708921e0a616.png",
    "gallery": [],
    "createdAt": 1777292954282,
    "status": "publicado"
  },
  {
    "id": "1777292989773",
    "title": "CORDA DE PULAR VERMELHA",
    "price": 1,
    "description": "CORDA VERMELHA ",
    "department": "cosmetics",
    "category": "Body Oil",
    "stock": 2,
    "image": "https://raw.githubusercontent.com/STAVARENG0/hs/main/products/1777292989773_1777292989909_baeae76b1001.png",
    "gallery": [],
    "createdAt": 1777292993894,
    "status": "publicado"
  },
  {
    "id": "1777293031592",
    "title": "CORDA PRETA ",
    "price": 1,
    "description": "CORDA  DE PULAR NA COR PRETA",
    "department": "fashion",
    "category": "fashion",
    "stock": 2,
    "image": "https://raw.githubusercontent.com/STAVARENG0/hs/main/products/1777293031592_1777293031232_2b62677aee03.png",
    "gallery": [],
    "createdAt": 1777293036034,
    "status": "publicado"
  }
]